pyoracc/__init__.py
pyoracc/atf/__init__.py
pyoracc/atf/parsetab.py
pyoracc/atf/cdli/__init__.py
pyoracc/atf/cdli/atflex.py
pyoracc/atf/cdli/atfyacc.py
pyoracc/atf/common/__init__.py
pyoracc/atf/common/atffile.py
pyoracc/atf/common/atflex.py
pyoracc/atf/common/atflexicon.py
pyoracc/atf/common/atfyacc.py
pyoracc/atf/oracc/__init__.py
pyoracc/atf/oracc/atflex.py
pyoracc/atf/oracc/atfyacc.py
pyoracc/model/__init__.py
pyoracc/model/comment.py
pyoracc/model/composite.py
pyoracc/model/corpus.py
pyoracc/model/line.py
pyoracc/model/link.py
pyoracc/model/link_reference.py
pyoracc/model/milestone.py
pyoracc/model/multilingual.py
pyoracc/model/note.py
pyoracc/model/oraccnamedobject.py
pyoracc/model/oraccobject.py
pyoracc/model/ruling.py
pyoracc/model/score.py
pyoracc/model/state.py
pyoracc/model/text.py
pyoracc/model/translation.py
pyoracc/wrapper/__init__.py
pyoracc/wrapper/cli.py
pyoracc/wrapper/segment.py
pyoracc-0.1.0.dist-info/LICENSE.txt
pyoracc-0.1.0.dist-info/METADATA
pyoracc-0.1.0.dist-info/RECORD
pyoracc-0.1.0.dist-info/WHEEL
pyoracc-0.1.0.dist-info/entry_points.txt
pyoracc-0.1.0.dist-info/top_level.txt
