Metadata-Version: 2.1
Name: pyoracc
Version: 0.1.0
Summary: Python tools for working with ORACC/CDLI ATF files
Home-page: https://github.com/ucl/pyoracc
Author: UCL Research IT Services
Author-email: rc-softdev@ucl.ac.uk
License: GPLv3
Download-URL: https://github.com/ucl/pyoracc/archive/master.tar.gz
Project-URL: Donating!, http://oracc.museum.upenn.edu/doc/about/contributing/
Project-URL: Source, https://github.com/oracc/pyoracc/
Project-URL: Bug Reports, https://github.com/oracc/pyoracc/issues
Project-URL: Help!, http://oracc.museum.upenn.edu/doc/help/index.html
Keywords: oracc cdli atf cuneiform parser
Platform: UNKNOWN
Classifier: Development Status :: 5 - Production/Stable
Classifier: Environment :: Console
Classifier: Intended Audience :: Developers
Classifier: Intended Audience :: Education
Classifier: Intended Audience :: Science/Research
Classifier: License :: OSI Approved :: GNU General Public License v3 (GPLv3)
Classifier: Operating System :: POSIX
Classifier: Operating System :: MacOS
Classifier: Operating System :: Unix
Classifier: Operating System :: Microsoft :: Windows
Classifier: Programming Language :: Python
Classifier: Programming Language :: Python :: 2
Classifier: Programming Language :: Python :: 3
Classifier: Topic :: Software Development :: Libraries :: Python Modules
Classifier: Topic :: Utilities
Requires-Python: >=2.6, !=3.0.*, !=3.1.*, !=3.2.*, <4
Provides-Extra: test
Provides-Extra: dev
Requires-Dist: click
Requires-Dist: mako
Requires-Dist: ply
Provides-Extra: dev
Requires-Dist: pytest; extra == 'dev'
Requires-Dist: pytest-cov; extra == 'dev'
Requires-Dist: codecov; extra == 'dev'
Requires-Dist: pycodestyle; extra == 'dev'
Provides-Extra: test
Requires-Dist: pytest; extra == 'test'
Requires-Dist: pytest-cov; extra == 'test'
Requires-Dist: codecov; extra == 'test'
Requires-Dist: pycodestyle; extra == 'test'
